adderall/__init__.py
adderall/bitnum.hy
adderall/debug.hy
adderall/dsl.hy
adderall/internal.hy
adderall/extra/__init__.py
adderall/extra/misc.hy
adderall/extra/zebra.hy
adderall/extra/cheezburger/__init__.py
adderall/extra/cheezburger/grumpy_cat.hy
adderall/extra/cheezburger/kitteh.hy
adderall-2.0.0.dist-info/METADATA
adderall-2.0.0.dist-info/RECORD
adderall-2.0.0.dist-info/WHEEL
adderall-2.0.0.dist-info/top_level.txt
