Metadata-Version: 2.1
Name: adderall
Version: 2.0.0
Summary: UNKNOWN
Home-page: https://github.com/algernon/adderall
Author: Gergely Nagy
Author-email: algernon@madhouse-project.org
License: LGPL-3
Platform: any
Classifier: Development Status :: 5 - Production/Stable
Classifier: Intended Audience :: Developers
Classifier: License :: DFSG approved
Classifier: License :: OSI Approved :: GNU Lesser General Public License v3 or later (LGPLv3+)
Classifier: Operating System :: OS Independent
Classifier: Programming Language :: Lisp
Classifier: Topic :: Software Development :: Libraries
Requires-Dist: hy (>=0.15)
Requires-Dist: monaxhyd (>=0.2.1)
